{
  "schema_version": "ace_playbook_v1",
  "family": "empirical_research_practice",
  "mode": "pgmr_lite",
  "created_at_utc": "2026-05-03T22:06:27.268635+00:00",
  "updated_at_utc": "2026-05-03T22:06:27.268635+00:00",
  "metadata": {
    "description": "Initial shared ACE playbook for Empirical Research Practice PGMR-lite experiments.",
    "source": "manual_initial_shared_playbook"
  },
  "bullets": [
    {
      "id": "global_any_output_format_initial",
      "family": "global",
      "mode": "any",
      "category": "output_format",
      "title": "Return only the query",
      "content": "Return only the final SPARQL or PGMR-lite query. Do not add explanations, markdown, or reasoning text.",
      "bullet_type": "hard_rule",
      "priority": 100,
      "enabled": true,
      "positive_pattern": null,
      "avoid": "Do not answer in natural language.",
      "applicability": [],
      "source": {
        "type": "manual_initial_rule"
      },
      "evidence_item_ids": [],
      "helpful_count": 0,
      "harmful_count": 0,
      "created_at_utc": "2026-05-03T22:06:27.268635+00:00",
      "updated_at_utc": "2026-05-03T22:06:27.268635+00:00"
    },
    {
      "id": "empirical_research_practice_pgmr_lite_pgmr_format_initial",
      "family": "empirical_research_practice",
      "mode": "pgmr_lite",
      "category": "pgmr_format",
      "title": "Use PGMR-lite placeholders only",
      "content": "Use pgmr:/pgmrc: placeholders from the PGMR prompt or memory. Do not generate real ORKG IDs in PGMR-lite mode.",
      "bullet_type": "hard_rule",
      "priority": 95,
      "enabled": true,
      "positive_pattern": null,
      "avoid": "Do not mix pgmr:/pgmrc: placeholders with orkgp:/orkgc:/orkgr: identifiers.",
      "applicability": [],
      "source": {
        "type": "manual_initial_rule"
      },
      "evidence_item_ids": [],
      "helpful_count": 0,
      "harmful_count": 0,
      "created_at_utc": "2026-05-03T22:06:27.268635+00:00",
      "updated_at_utc": "2026-05-03T22:06:27.268635+00:00"
    },
    {
      "id": "empirical_research_practice_pgmr_lite_contribution_pattern_initial",
      "family": "empirical_research_practice",
      "mode": "pgmr_lite",
      "category": "contribution_pattern",
      "title": "Use Empirical Research Practice contribution pattern",
      "content": "Connect papers to empirical research practice contributions before accessing family-specific fields.",
      "bullet_type": "template_pattern",
      "priority": 90,
      "enabled": true,
      "positive_pattern": "?paper pgmr:has_contribution ?contribution . ?contribution a pgmrc:empirical_research_practice_contribution .",
      "avoid": "Do not attach empirical research, venue, method, practice, or evidence properties directly to ?paper.",
      "applicability": [],
      "source": {
        "type": "manual_initial_rule"
      },
      "evidence_item_ids": [],
      "helpful_count": 0,
      "harmful_count": 0,
      "created_at_utc": "2026-05-03T22:06:27.268635+00:00",
      "updated_at_utc": "2026-05-03T22:06:27.268635+00:00"
    }
  ]
}